{"cameraMode":{"drawMode":0,"name":"Shaded","section":"Shading Mode"},"sceneLighting":true,"audioPlay":false,"sceneViewState":{"showFog":true,"showMaterialUpdate":false,"showSkybox":true,"showFlares":true,"showImageEffects":true,"showParticleSystems":true},"in2DMode":false,"pivot":{"x":-10.980134963989258,"y":23.866384506225587,"z":-37.6655387878418},"rotation":{"x":0.14943630993366242,"y":0.010064088739454747,"z":-0.0015597556484863163,"w":0.9887539148330689},"size":60.18327331542969,"orthographic":false}